{"cameraMode":{"drawMode":0,"name":"Shaded","section":"Shading Mode"},"sceneLighting":true,"audioPlay":false,"sceneViewState":{"showFog":true,"showMaterialUpdate":false,"showSkybox":true,"showFlares":true,"showImageEffects":true,"showParticleSystems":true,"showVisualEffectGraphs":true,"m_FxEnabled":true},"in2DMode":false,"pivot":{"x":-0.32683420181274416,"y":1.6385620832443238,"z":-1.1399998664855958},"rotation":{"x":0.0,"y":-0.7071068286895752,"z":0.0,"w":0.7071068286895752},"size":16.744915008544923,"orthographic":false}